Workbook

Sheet Read Me
A1: Denver Metro Healthcare Market — Account Universe
A2: Prepared for Kristin Boothart | Hillyard, Inc. — District Sales Manager, Denver | Compiled August 14, 2026
A5: WHAT'S IN THIS WORKBOOK
A6: Hospital Systems | B6: Roll-up of every parent health system, ranked by total licensed beds. Live formulas pull from the Hospitals tab.
A7: Hospitals | B7: Every acute-care, children's, and specialty hospital, grouped by corporate parent, largest to smallest.
A8: LTC Operators | B8: Roll-up of every long-term care corporate operator, ranked by total licensed beds across their Colorado portfolio.
A9: LTC Facilities | B9: ~250 skilled nursing, assisted living, memory care, and CCRC facilities grouped by the company that runs them.
A10: Other Facilities | B10: Rehab hospitals, LTACHs, psychiatric hospitals, surgery centers, dialysis, freestanding ERs, urgent care, clinic networks, cancer centers, imaging, hospice, occupational health.
A12: THREE OWNERSHIP FACTS THAT INVALIDATE MOST DENVER HOSPITAL LISTS
A13: 1. Centura is gone. | B13: Centura Health dissolved in 2023-24. AdventHealth took exactly 5 hospitals (Porter, Littleton, Parker, Avista, Castle Rock); CommonSpirit took the rest. Any list still saying 'Centura' is stale — and using that name in a meeting will cost you credibility.
A14: 2. HCA renamed 9 hospitals Oct 2024. | B14: 'The Medical Center of Aurora' is now HCA HealthONE Aurora. 'North Suburban Medical Center' is now HCA HealthONE Mountain Ridge. Both old names still circulate widely.
A15: 3. A major JV is pending. | B15: AdventHealth and Intermountain signed a definitive agreement on Aug 5, 2026 to combine AdventHealth's 5 Denver hospitals with 3 of Intermountain's (Good Samaritan, Lutheran, Platte Valley). AdventHealth gets majority interest and runs daily ops. Saint Joseph is EXCLUDED and stays with Intermountain. Expected close early 2027, pending CO Attorney General review. If it closes, that's a ~1,940-bed system and the #3 player in the metro — and it means purchasing authority for 8 hospitals is about to move.
A17: HOW TO READ THE COLUMNS
A18: Region | B18: Metro = 7-county Denver metro. Extended = Front Range within roughly a 50-90 minute drive (Fort Collins, Loveland, Greeley, Colorado Springs). Outside metro = the rest of Colorado, included only where an operator's portfolio spans the state.
A19: Licensed Beds | B19: State-authorized maximum, not staffed beds. Staffed counts typically run 25-50% lower. Use licensed beds for sizing the building; ask about census when sizing the order.
A20: Parent / Operator | B20: The corporate entity that controls purchasing. This is the organizing principle of the whole workbook — one contract at this level can cover dozens of buildings.
A21: Notes (add your own) | B21: Blank column for your working notes. Example: "Incumbent = Bunzl, GPO through Premier, contract renews Jun-2027, met w/ EVS Dir 9/12".
A23: WHERE THE LEVERAGE IS
A24: Hospitals | B24: Six systems control roughly 90% of metro beds. HCA HealthONE and UCHealth are effectively tied for #1 and are within ~50 beds of each other. HCA is for-profit and buys through national GPO contracts out of Nashville; UCHealth, Denver Health, and Children's are more locally decided. Know which door you're knocking on.
A25: Long-term care | B25: Five phone calls cover roughly a third of Colorado's licensed LTC beds: Ensign/Endura, Life Care Centers, PACS Group, Vivage-Beecan, and Stellar. All five have centralized purchasing.
A26: A trap worth knowing | B26: Vivage-Beecan is the management company, but many of its buildings are LICENSED under 'Long Peak Operating Company' in state and CMS records. If you research by licensee you will call the wrong office. Purchasing sits with Vivage in Glendale.
A27: Management companies | B27: Cappella Living Solutions and WellAge manage buildings they do not own — so they control purchasing for facilities that will never show up under their name in a property search. Higher-leverage calls than the individual buildings.
A28: Nonprofit CCRC cluster | B28: South metro (Christian Living Communities, Wind Crest, Vi at Highlands Ranch, Covenant Living, Holly Creek, Someren Glen) — multi-building campuses where one contract covers independent living, assisted living, memory care, skilled nursing, plus commercial kitchens and large common areas.
A29: DaVita | B29: Headquartered in Denver at 2000 16th St, with ~2,600 US clinics and ~30 in the metro. A national account whose decision-makers are in your new backyard.
A31: CAVEATS
B32: 1. Licensed vs staffed beds conflict across sources. Where a hospital publishes its own current figure, that was used over the 2018 Medicare cost report.
B33: 2. Post-acute and behavioral health ownership churns through private-equity transactions faster than public sources update. Treat the Other Facilities tab's parent column as a starting point, not gospel.
B34: 3. Ambulatory surgery centers are almost universally physician-JV LLCs. USPI, SCA Health, AmSurg, and Surgery Partners all hold Colorado stakes that are not publicly attributable by site.
B35: 4. Urgent care is not a state license class, so those counts come from company websites and are the softest numbers here.
B36: 5. Independent living units at CCRCs are generally unlicensed and therefore absent from state bed data — campuses like Wind Crest (~1,300-1,500 IL apartments) are far larger than their licensed bed count suggests.
A38: SOURCES
B39: CMS Care Compare nursing home provider dataset (July 2026); CDPHE Health Facilities licensing registry (~5,014 facilities); Becker's Hospital Review; Healthcare Dive; Colorado Sun; Fierce Healthcare; system and facility websites (HCA HealthONE, UCHealth, CommonSpirit Mountain Region, AdventHealth, Intermountain, Denver Health, Children's Colorado); Colorado Health Care Association; Colorado Community Health Network.

Sheet Hospital Systems
A1: Hospital Systems — Ranked by Total Licensed Beds
A2: Live roll-up from the Hospitals tab. This is your call list: six systems control roughly 90% of metro beds.
A4: # | B4: Parent System | C4: Ownership Type | D4: Hospitals | E4: Total Licensed Beds | F4: Notes (add your own)
A5: 1 | B5: HCA HealthONE (HCA Healthcare) | C5: For-profit, publicly traded (NYSE: HCA) | D5: =COUNTIF(Hospitals!$D$5:$D$58,$B5) -> 8 | E5: =SUMIF(Hospitals!$D$5:$D$58,$B5,Hospitals!$E$5:$E$58) -> 2471 | F5: Largest metro system. Buys through national GPO contracts out of Nashville — local EVS directors influence, corporate decides. Renamed 9 CO hospitals Oct 2024.
A6: 2 | B6: UCHealth | C6: Nonprofit / state-affiliated | D6: =COUNTIF(Hospitals!$D$5:$D$58,$B6) -> 10 | E6: =SUMIF(Hospitals!$D$5:$D$58,$B6,Hospitals!$E$5:$E$58) -> 2318 | F6: Effectively tied with HCA for #1. Academic flagship at Anschutz. More locally decided than HCA.
A7: 3 | B7: CommonSpirit Health (Mountain Region) | C7: Nonprofit Catholic | D7: =COUNTIF(Hospitals!$D$5:$D$58,$B7) -> 7 | E7: =SUMIF(Hospitals!$D$5:$D$58,$B7,Hospitals!$E$5:$E$58) -> 1324 | F7: Took 12 of the former Centura Colorado hospitals in the 2023-24 split. National Catholic system, Chicago HQ.
A8: 4 | B8: AdventHealth Rocky Mountain Region | C8: Nonprofit, Seventh-day Adventist | D8: =COUNTIF(Hospitals!$D$5:$D$58,$B8) -> 5 | E8: =SUMIF(Hospitals!$D$5:$D$58,$B8,Hospitals!$E$5:$E$58) -> 978 | F8: Took exactly 5 Centura hospitals. PENDING JV with Intermountain — will run 8 Denver hospitals if it closes early 2027.
A9: 5 | B9: Intermountain Health | C9: Nonprofit (formerly SCL Health) | D9: =COUNTIF(Hospitals!$D$5:$D$58,$B9) -> 4 | E9: =SUMIF(Hospitals!$D$5:$D$58,$B9,Hospitals!$E$5:$E$58) -> 958 | F9: 3 of its 4 CO hospitals are in the pending AdventHealth JV. Saint Joseph stays with Intermountain.
A10: 6 | B10: Children's Hospital Colorado | C10: Independent nonprofit | D10: =COUNTIF(Hospitals!$D$5:$D$58,$B10) -> 4 | E10: =SUMIF(Hospitals!$D$5:$D$58,$B10,Hospitals!$E$5:$E$58) -> 543 | F10: Only ACS-verified Level I Pediatric Trauma Center in Colorado. Top-10 nationally.
A11: 7 | B11: Denver Health (public authority) | C11: Public safety-net authority | D11: =COUNTIF(Hospitals!$D$5:$D$58,$B11) -> 1 | E11: =SUMIF(Hospitals!$D$5:$D$58,$B11,Hospitals!$E$5:$E$58) -> 525 | F11: Public safety-net. Political subdivision of the State of Colorado — expect public procurement rules and formal bidding.
A12: 8 | B12: US Dept. of Veterans Affairs | C12: Federal | D12: =COUNTIF(Hospitals!$D$5:$D$58,$B12) -> 1 | E12: =SUMIF(Hospitals!$D$5:$D$58,$B12,Hospitals!$E$5:$E$58) -> 187 | F12: Federal procurement. Requires SAM registration and likely a GSA/FSS schedule or VA contract vehicle.
A13: 9 | B13: Boulder Community Health (independent) | C13: Independent nonprofit | D13: =COUNTIF(Hospitals!$D$5:$D$58,$B13) -> 1 | E13: =SUMIF(Hospitals!$D$5:$D$58,$B13,Hospitals!$E$5:$E$58) -> 167 | F13: One of Colorado's last independent community hospitals. Local decision-making.
A14: 10 | B14: Craig Hospital (independent nonprofit) | C14: Independent nonprofit | D14: =COUNTIF(Hospitals!$D$5:$D$58,$B14) -> 1 | E14: =SUMIF(Hospitals!$D$5:$D$58,$B14,Hospitals!$E$5:$E$58) -> 93 | F14: Independent nonprofit, nationally ranked neurorehab. Single-site decision.
A15: 11 | B15: National Jewish Health (independent) | C15: Independent nonprofit | D15: =COUNTIF(Hospitals!$D$5:$D$58,$B15) -> 1 | E15: =SUMIF(Hospitals!$D$5:$D$58,$B15,Hospitals!$E$5:$E$58) -> 46 | F15: #1 respiratory hospital in the US. Single site; partners with Saint Joseph.
B16: TOTAL | D16: =SUM(D5:D15) -> 43 | E16: =SUM(E5:E15) -> 9610
B18: Top 6 systems as % of all listed beds: | E18: =SUM(E5:E10)/E16 -> 0.89406868
B20: If the AdventHealth-Intermountain JV closes (expected early 2027), AdventHealth + Good Samaritan + Lutheran + Platte Valley combine into a ~1,940-bed system, and Intermountain drops to one Colorado hospital.

Sheet Hospitals
A1: Hospitals — Denver Metro and Front Range, by Corporate Parent
A2: Grouped by parent health system (systems ordered by total beds), hospitals within each system ordered largest to smallest.
A4: # | B4: Hospital | C4: City | D4: Parent System | E4: Licensed Beds | F4: Type | G4: Region | H4: Notes (add your own)
A5: HCA HealthONE (HCA Healthcare) — 8 hospital(s), 2,471 licensed beds
A6: 1 | B6: HCA HealthONE Presbyterian St. Luke's | C6: Denver | D6: HCA HealthONE (HCA Healthcare) | E6: 680 | F6: General acute / tertiary | G6: Metro | H6: Solid organ + bone marrow transplant; Colorado Blood Cancer Institute
A7: 2 | B7: HCA HealthONE Swedish | C7: Englewood | D7: HCA HealthONE (HCA Healthcare) | E7: 504 | F7: General acute | G7: Metro | H7: LEVEL I TRAUMA; burn center; state's first Comprehensive Stroke Center; 21 ORs
A8: 3 | B8: HCA HealthONE Rose | C8: Denver | D8: HCA HealthONE (HCA Healthcare) | E8: 422 | F8: General acute | G8: Metro | H8: Magnet since 2017; women's services / NICU
A9: 4 | B9: HCA HealthONE Aurora | C9: Aurora | D9: HCA HealthONE (HCA Healthcare) | E9: 346 | F9: General acute | G9: Metro | H9: RENAMED Oct 2024 (was The Medical Center of Aurora). Level II Trauma; 84-bed cardiac tower
A10: 5 | B10: HCA HealthONE Sky Ridge | C10: Lone Tree | D10: HCA HealthONE (HCA Healthcare) | E10: 284 | F10: General acute | G10: Metro | H10: Level II Trauma; Douglas County's first hospital
A11: 6 | B11: HCA HealthONE Mountain Ridge | C11: Thornton | D11: HCA HealthONE (HCA Healthcare) | E11: 157 | F11: General acute | G11: Metro | H11: RENAMED Oct 2024 (was North Suburban Medical Center). Level II Trauma
A12: 7 | B12: HCA HealthONE Spalding Rehabilitation | C12: Aurora | D12: HCA HealthONE (HCA Healthcare) | E12: 78 | F12: Inpatient rehab | G12: Metro | H12: Colorado's first licensed rehab hospital (1965)
A13: 8 | B13: HCA HealthONE Rocky Mountain Children's | C13: Denver | D13: HCA HealthONE (HCA Healthcare) | F13: Children's | G13: Metro | H13: Hospital-within-hospital at Presbyterian St. Luke's (~53 beds) - NOT counted separately
A14: UCHealth — 10 hospital(s), 2,318 licensed beds
A15: 9 | B15: UCHealth University of Colorado Hospital | C15: Aurora | D15: UCHealth | E15: 698 | F15: Academic medical center | G15: Metro | H15: LEVEL I TRAUMA; principal teaching hospital, CU School of Medicine; Anschutz campus
A16: 10 | B16: UCHealth Memorial Hospital Central | C16: Colorado Springs | D16: UCHealth | E16: 413 | F16: General acute | G16: Extended | H16: Level I Trauma; Comprehensive Stroke Center
A17: 11 | B17: UCHealth Memorial Hospital North | C17: Colorado Springs | D17: UCHealth | E17: 300 | F17: General acute | G17: Extended | H17: Approximate - shares a 713-bed combined license with Central
A18: 12 | B18: UCHealth Poudre Valley Hospital | C18: Fort Collins | D18: UCHealth | E18: 270 | F18: General acute | G18: Extended | H18: Sources vary 270-300; NICU; hyperbarics
A19: 13 | B19: UCHealth Medical Center of the Rockies | C19: Loveland | D19: UCHealth | E19: 216 | F19: General acute | G19: Extended | H19: Level I Trauma; cardiac specialty; LifeLine air transport
A20: 14 | B20: UCHealth Highlands Ranch Hospital | C20: Highlands Ranch | D20: UCHealth | E20: 147 | F20: General acute | G20: Metro | H20: Opened 2019; $119M expansion underway
A21: 15 | B21: UCHealth Longs Peak Hospital | C21: Longmont | D21: UCHealth | E21: 89 | F21: General acute | G21: Metro | H21: Primary Stroke Center
A22: 16 | B22: UCHealth Greeley Hospital | C22: Greeley | D22: UCHealth | E22: 88 | F22: General acute | G22: Extended | H22: Opened 2019; expanded 2023
A23: 17 | B23: UCHealth Grandview Hospital | C23: Colorado Springs | D23: UCHealth | E23: 57 | F23: General acute / ortho | G23: Extended | H23: Joint Commission-certified hip & knee replacement
A24: 18 | B24: UCHealth Broomfield Hospital | C24: Broomfield | D24: UCHealth | E24: 40 | F24: Community acute | G24: Metro | H24: Opened 2016
A25: CommonSpirit Health (Mountain Region) — 7 hospital(s), 1,324 licensed beds
A26: 19 | B26: CommonSpirit St. Francis Hospital | C26: Colorado Springs | D26: CommonSpirit Health (Mountain Region) | E26: 317 | F26: General acute | G26: Extended | H26: Level III Trauma; Level III NICU; Flight For Life home base
A27: 20 | B27: CommonSpirit Penrose Hospital | C27: Colorado Springs | D27: CommonSpirit Health (Mountain Region) | E27: 300 | F27: General acute | G27: Extended | H27: Level II state / Level I ACS-verified trauma; cancer & cardiac referral center
A28: 21 | B28: CommonSpirit St. Anthony Hospital | C28: Lakewood | D28: CommonSpirit Health (Mountain Region) | E28: 237 | F28: General acute | G28: Metro | H28: LEVEL I TRAUMA + Comprehensive Stroke; HQ of Flight For Life Colorado
A29: 22 | B29: CommonSpirit St. Anthony North Hospital | C29: Westminster | D29: CommonSpirit Health (Mountain Region) | E29: 206 | F29: General acute | G29: Metro | H29: Level III Trauma; new bed tower 2024 (237 at full build-out)
A30: 23 | B30: Longmont United Hospital | C30: Longmont | D30: CommonSpirit Health (Mountain Region) | E30: 186 | F30: General acute | G30: Metro | H30: Level III Trauma; Level II NICU. Confirmed CommonSpirit, not AdventHealth
A31: 24 | B31: OrthoColorado Hospital | C31: Lakewood | D31: CommonSpirit Health (Mountain Region) | E31: 48 | F31: Specialty - ortho/spine | G31: Metro | H31: JV with local ortho practices; only ortho/spine specialty hospital in the Rockies
A32: 25 | B32: CommonSpirit St. Francis Hospital - Interquest | C32: Colorado Springs | D32: CommonSpirit Health (Mountain Region) | E32: 30 | F32: Neighborhood acute | G32: Extended | H32: Approximate; newer small-format hospital
A33: AdventHealth Rocky Mountain Region — 5 hospital(s), 978 licensed beds
A34: 26 | B34: AdventHealth Porter | C34: Denver | D34: AdventHealth Rocky Mountain Region | E34: 368 | F34: General acute / tertiary | G34: Metro | H34: Level III Trauma; organ transplant (kidney/liver/pancreas); behavioral health; teaching hospital
A35: 27 | B35: AdventHealth Littleton | C35: Littleton | D35: AdventHealth Rocky Mountain Region | E35: 231 | F35: General acute / tertiary | G35: Metro | H35: Level II Trauma; Comprehensive Stroke; heart & vascular tower opened Aug 2025
A36: 28 | B36: AdventHealth Parker | C36: Parker | D36: AdventHealth Rocky Mountain Region | E36: 179 | F36: General acute / tertiary | G36: Metro | H36: Level II Trauma; $300M seven-story tower broke ground Jan 2025
A37: 29 | B37: AdventHealth Avista | C37: Louisville | D37: AdventHealth Rocky Mountain Region | E37: 114 | F37: General acute | G37: Metro | H37: Level III Trauma; replacement hospital planned at 123 beds
A38: 30 | B38: AdventHealth Castle Rock | C38: Castle Rock | D38: AdventHealth Rocky Mountain Region | E38: 86 | F38: General acute | G38: Metro | H38: Level III Trauma; cancer center opened Feb 2026
A39: Intermountain Health — 4 hospital(s), 958 licensed beds
A40: 31 | B40: Intermountain Health Saint Joseph Hospital | C40: Denver | D40: Intermountain Health | E40: 400 | F40: General acute | G40: Metro | H40: EXCLUDED from the pending AdventHealth JV - stays with Intermountain
A41: 32 | B41: Intermountain Health Good Samaritan Hospital | C41: Lafayette | D41: Intermountain Health | E41: 234 | F41: General acute | G41: Metro | H41: Level II Trauma. IN PENDING ADVENTHEALTH JV
A42: 33 | B42: Intermountain Health Lutheran Hospital | C42: Wheat Ridge | D42: Intermountain Health | E42: 226 | F42: General acute | G42: Metro | H42: Level II Trauma; brand-new replacement campus opened Aug 2024. IN PENDING ADVENTHEALTH JV
A43: 34 | B43: Intermountain Health Platte Valley Hospital | C43: Brighton | D43: Intermountain Health | E43: 98 | F43: General acute | G43: Metro | H43: IN PENDING ADVENTHEALTH JV
A44: Children's Hospital Colorado — 4 hospital(s), 543 licensed beds
A45: 35 | B45: Children's Hospital Colorado - Anschutz | C45: Aurora | D45: Children's Hospital Colorado | E45: 444 | F45: Children's | G45: Metro | H45: Only ACS-verified Level I Pediatric Trauma Center in Colorado; Level IV NICU; US News top-10
A46: 36 | B46: Children's Hospital Colorado - Colorado Springs | C46: Colorado Springs | D46: Children's Hospital Colorado | E46: 99 | F46: Children's | G46: Extended | H46: Approximate; full inpatient pediatric
A47: 37 | B47: Children's Hospital Colorado - North Campus | C47: Broomfield | D47: Children's Hospital Colorado | F47: Children's - outpatient/ED | G47: Metro | H47: Primarily ED and outpatient
A48: 38 | B48: Children's Hospital Colorado - South Campus | C48: Highlands Ranch | D48: Children's Hospital Colorado | F48: Children's - outpatient/ED | G48: Metro | H48: Primarily ED and outpatient
A49: Denver Health (public authority) — 1 hospital(s), 525 licensed beds
A50: 39 | B50: Denver Health Medical Center | C50: Denver | D50: Denver Health (public authority) | E50: 525 | F50: General acute / safety-net | G50: Metro | H50: LEVEL I ADULT TRAUMA / Level II Pediatric. Rocky Mountain Poison & Drug Center; city 911/EMS
A51: US Dept. of Veterans Affairs — 1 hospital(s), 187 licensed beds
A52: 40 | B52: Rocky Mountain Regional VA Medical Center | C52: Aurora | D52: US Dept. of Veterans Affairs | E52: 187 | F52: Federal general acute | G52: Metro | H52: VA Eastern Colorado; spinal cord injury & polytrauma centers
A53: Boulder Community Health (independent) — 1 hospital(s), 167 licensed beds
A54: 41 | B54: Boulder Community Foothills Hospital | C54: Boulder | D54: Boulder Community Health (independent) | E54: 167 | F54: General acute | G54: Metro | H54: Level II Trauma; one of Colorado's last independent community hospitals
A55: Craig Hospital (independent nonprofit) — 1 hospital(s), 93 licensed beds
A56: 42 | B56: Craig Hospital | C56: Englewood | D56: Craig Hospital (independent nonprofit) | E56: 93 | F56: Specialty - neurorehab | G56: Metro | H56: Nationally top-ranked spinal cord injury / TBI rehab & research
A57: National Jewish Health (independent) — 1 hospital(s), 46 licensed beds
A58: 43 | B58: National Jewish Health | C58: Denver | D58: National Jewish Health (independent) | E58: 46 | F58: Specialty - respiratory | G58: Metro | H58: #1 respiratory hospital in the US (US News); partners with Saint Joseph Hospital
B59: TOTAL — all hospitals listed | E59: =SUM(E5:E58) -> 9610
B61: Excluded as outside the Front Range corridor: UCHealth Parkview (Pueblo, 350) and Parkview Pueblo West; CommonSpirit St. Anthony Summit (Frisco), St. Mary-Corwin (Pueblo), Mercy (Durango), St. Thomas More (Canon City), St. Elizabeth (Fort Morgan); UCHealth Pikes Peak Regional (Woodland Park) and Yampa Valley (Steamboat Springs).
B62: Kaiser Permanente Colorado owns NO hospitals in the state — it contracts for inpatient care. Big provider, zero beds. See the Other Facilities tab for its 34 medical offices.

Sheet LTC Operators
A1: Long-Term Care Operators — Ranked by Total Licensed Beds
A2: Live roll-up from the LTC Facilities tab. One contract at this level can cover dozens of buildings.
A4: # | B4: Corporate Operator | C4: Facilities | D4: Total Licensed Beds | E4: Metro Facilities | F4: Notes (add your own)
A5: 1 | B5: The Ensign Group (Endura Healthcare) | C5: =COUNTIF('LTC Facilities'!$D$5:$D$316,$B5) -> 33 | D5: =SUMIF('LTC Facilities'!$D$5:$D$316,$B5,'LTC Facilities'!$E$5:$E$316) -> 3664 | E5: =COUNTIFS('LTC Facilities'!$D$5:$D$316,$B5,'LTC Facilities'!$G$5:$G$316,"Metro") -> 22 | F5: LARGEST LTC operator in Colorado. Decentralized by design — each building is its own operating subsidiary with local P&L authority — but Endura Healthcare (Dave Jorgensen) is the right entry point for a portfolio deal.
A6: 2 | B6: Life Care Centers of America | C6: =COUNTIF('LTC Facilities'!$D$5:$D$316,$B6) -> 22 | D6: =SUMIF('LTC Facilities'!$D$5:$D$316,$B6,'LTC Facilities'!$E$5:$E$316) -> 2929 | E6: =COUNTIFS('LTC Facilities'!$D$5:$D$316,$B6,'LTC Facilities'!$G$5:$G$316,"Metro") -> 12 | F6: Cleveland TN, privately held (Forrest Preston). Centralized purchasing.
A7: 3 | B7: PACS Group (NYSE: PACS) | C7: =COUNTIF('LTC Facilities'!$D$5:$D$316,$B7) -> 19 | D7: =SUMIF('LTC Facilities'!$D$5:$D$316,$B7,'LTC Facilities'!$E$5:$E$316) -> 2409 | E7: =COUNTIFS('LTC Facilities'!$D$5:$D$316,$B7,'LTC Facilities'!$G$5:$G$316,"Metro") -> 14 | F7: Utah-based public company. Brands everything '...Post Acute'. Has been under Colorado media and regulatory scrutiny.
A8: 4 | B8: Vivage-Beecan Senior Living | C8: =COUNTIF('LTC Facilities'!$D$5:$D$316,$B8) -> 23 | D8: =SUMIF('LTC Facilities'!$D$5:$D$316,$B8,'LTC Facilities'!$E$5:$E$316) -> 1909 | E8: =COUNTIFS('LTC Facilities'!$D$5:$D$316,$B8,'LTC Facilities'!$G$5:$G$316,"Metro") -> 15 | F8: COLORADO-BASED (Glendale). Merged with Beecan Feb 2023. WATCH OUT: many buildings are licensed under 'Long Peak Operating Company' in state/CMS records — purchasing sits with Vivage.
A9: 5 | B9: Stellar Senior Living | C9: =COUNTIF('LTC Facilities'!$D$5:$D$316,$B9) -> 12 | D9: =SUMIF('LTC Facilities'!$D$5:$D$316,$B9,'LTC Facilities'!$E$5:$E$316) -> 1646 | E9: =COUNTIFS('LTC Facilities'!$D$5:$D$316,$B9,'LTC Facilities'!$G$5:$G$316,"Metro") -> 5 | F9: Utah-based but Colorado is its largest state. Mixed SNF + AL/MC portfolio — good single-contract target.
A10: 6 | B10: MorningStar Senior Living (Denver HQ) | C10: =COUNTIF('LTC Facilities'!$D$5:$D$316,$B10) -> 15 | D10: =SUMIF('LTC Facilities'!$D$5:$D$316,$B10,'LTC Facilities'!$E$5:$E$316) -> 1476 | E10: =COUNTIFS('LTC Facilities'!$D$5:$D$316,$B10,'LTC Facilities'!$G$5:$G$316,"Metro") -> 11 | F10: HEADQUARTERED IN DENVER. AL/IL/MC only, no skilled nursing. 40+ communities across the West.
A11: 7 | B11: Brookdale Senior Living | C11: =COUNTIF('LTC Facilities'!$D$5:$D$316,$B11) -> 12 | D11: =SUMIF('LTC Facilities'!$D$5:$D$316,$B11,'LTC Facilities'!$E$5:$E$316) -> 1225 | E11: =COUNTIFS('LTC Facilities'!$D$5:$D$316,$B11,'LTC Facilities'!$G$5:$G$316,"Metro") -> 9 | F11: Largest US senior living operator. Mostly AL/IL/MC in Colorado plus two SNF units. 11 additional IL-only communities carry no licensed beds.
A12: 8 | B12: Independent | C12: =COUNTIF('LTC Facilities'!$D$5:$D$316,$B12) -> 6 | D12: =SUMIF('LTC Facilities'!$D$5:$D$316,$B12,'LTC Facilities'!$E$5:$E$316) -> 1113 | E12: =COUNTIFS('LTC Facilities'!$D$5:$D$316,$B12,'LTC Facilities'!$G$5:$G$316,"Metro") -> 6 | F12: Large single-site buildings with no corporate parent — local decision-makers, faster sales cycles, but one building per contract.
A13: 9 | B13: Bello / Maze / Swain / Myers family group (Accel) | C13: =COUNTIF('LTC Facilities'!$D$5:$D$316,$B13) -> 9 | D13: =SUMIF('LTC Facilities'!$D$5:$D$316,$B13,'LTC Facilities'!$E$5:$E$316) -> 709 | E13: =COUNTIFS('LTC Facilities'!$D$5:$D$316,$B13,'LTC Facilities'!$G$5:$G$316,"Metro") -> 1
A14: 10 | B14: Sunrise Senior Living | C14: =COUNTIF('LTC Facilities'!$D$5:$D$316,$B14) -> 6 | D14: =SUMIF('LTC Facilities'!$D$5:$D$316,$B14,'LTC Facilities'!$E$5:$E$316) -> 675 | E14: =COUNTIFS('LTC Facilities'!$D$5:$D$316,$B14,'LTC Facilities'!$G$5:$G$316,"Metro") -> 6 | F14: 6 communities, ALL in the Denver metro. Tight geographic cluster.
A15: 11 | B15: Bethesda Senior Living Communities | C15: =COUNTIF('LTC Facilities'!$D$5:$D$316,$B15) -> 6 | D15: =SUMIF('LTC Facilities'!$D$5:$D$316,$B15,'LTC Facilities'!$E$5:$E$316) -> 646 | E15: =COUNTIFS('LTC Facilities'!$D$5:$D$316,$B15,'LTC Facilities'!$G$5:$G$316,"Metro") -> 1 | F15: Colorado Springs nonprofit. Only one metro building (Thornton).
A16: 12 | B16: Veritas Management Group | C16: =COUNTIF('LTC Facilities'!$D$5:$D$316,$B16) -> 8 | D16: =SUMIF('LTC Facilities'!$D$5:$D$316,$B16,'LTC Facilities'!$E$5:$E$316) -> 636 | E16: =COUNTIFS('LTC Facilities'!$D$5:$D$316,$B16,'LTC Facilities'!$G$5:$G$316,"Metro") -> 3
A17: 13 | B17: Centennial Healthcare | C17: =COUNTIF('LTC Facilities'!$D$5:$D$316,$B17) -> 8 | D17: =SUMIF('LTC Facilities'!$D$5:$D$316,$B17,'LTC Facilities'!$E$5:$E$316) -> 610 | E17: =COUNTIFS('LTC Facilities'!$D$5:$D$316,$B17,'LTC Facilities'!$G$5:$G$316,"Metro") -> 0
A18: 14 | B18: Madison Creek Partners | C18: =COUNTIF('LTC Facilities'!$D$5:$D$316,$B18) -> 8 | D18: =SUMIF('LTC Facilities'!$D$5:$D$316,$B18,'LTC Facilities'!$E$5:$E$316) -> 596 | E18: =COUNTIFS('LTC Facilities'!$D$5:$D$316,$B18,'LTC Facilities'!$G$5:$G$316,"Metro") -> 2
A19: 15 | B19: State of Colorado (Veterans Community Living Centers) | C19: =COUNTIF('LTC Facilities'!$D$5:$D$316,$B19) -> 5 | D19: =SUMIF('LTC Facilities'!$D$5:$D$316,$B19,'LTC Facilities'!$E$5:$E$316) -> 554 | E19: =COUNTIFS('LTC Facilities'!$D$5:$D$316,$B19,'LTC Facilities'!$G$5:$G$316,"Metro") -> 1 | F19: Operated by Colorado Dept. of Human Services. State procurement rules apply.
A20: 16 | B20: Columbine Health Systems | C20: =COUNTIF('LTC Facilities'!$D$5:$D$316,$B20) -> 5 | D20: =SUMIF('LTC Facilities'!$D$5:$D$316,$B20,'LTC Facilities'!$E$5:$E$316) -> 500 | E20: =COUNTIFS('LTC Facilities'!$D$5:$D$316,$B20,'LTC Facilities'!$G$5:$G$316,"Metro") -> 0 | F20: Family-owned, Fort Collins/Larimer County only. Not metro.
A21: 17 | B21: Ciel Senior Living | C21: =COUNTIF('LTC Facilities'!$D$5:$D$316,$B21) -> 5 | D21: =SUMIF('LTC Facilities'!$D$5:$D$316,$B21,'LTC Facilities'!$E$5:$E$316) -> 482 | E21: =COUNTIFS('LTC Facilities'!$D$5:$D$316,$B21,'LTC Facilities'!$G$5:$G$316,"Metro") -> 5 | F21: 5 communities, all Denver metro. Several licensed under legal entity names (Ridge Pinehurst LLC, Stonebridge Senior LLC) — hard to find by brand.
A22: 18 | B22: Christian Living Communities / Cappella | C22: =COUNTIF('LTC Facilities'!$D$5:$D$316,$B22) -> 7 | D22: =SUMIF('LTC Facilities'!$D$5:$D$316,$B22,'LTC Facilities'!$E$5:$E$316) -> 439 | E22: =COUNTIFS('LTC Facilities'!$D$5:$D$316,$B22,'LTC Facilities'!$G$5:$G$316,"Metro") -> 4 | F22: Greenwood Village nonprofit. Cappella Living Solutions is its third-party MANAGEMENT arm — it controls purchasing for buildings it doesn't own.
A23: 19 | B23: Balfour Senior Living (Kisco Senior Living) | C23: =COUNTIF('LTC Facilities'!$D$5:$D$316,$B23) -> 6 | D23: =SUMIF('LTC Facilities'!$D$5:$D$316,$B23,'LTC Facilities'!$E$5:$E$316) -> 433 | E23: =COUNTIFS('LTC Facilities'!$D$5:$D$316,$B23,'LTC Facilities'!$G$5:$G$316,"Metro") -> 6 | F23: Colorado-founded (Louisville CO), now owned by Kisco. All 6 communities in metro/Boulder County.
A24: 20 | B24: Ivy Living | C24: =COUNTIF('LTC Facilities'!$D$5:$D$316,$B24) -> 4 | D24: =SUMIF('LTC Facilities'!$D$5:$D$316,$B24,'LTC Facilities'!$E$5:$E$316) -> 404 | E24: =COUNTIFS('LTC Facilities'!$D$5:$D$316,$B24,'LTC Facilities'!$G$5:$G$316,"Metro") -> 2
A25: 21 | B25: Frontline Management | C25: =COUNTIF('LTC Facilities'!$D$5:$D$316,$B25) -> 5 | D25: =SUMIF('LTC Facilities'!$D$5:$D$316,$B25,'LTC Facilities'!$E$5:$E$316) -> 389 | E25: =COUNTIFS('LTC Facilities'!$D$5:$D$316,$B25,'LTC Facilities'!$G$5:$G$316,"Metro") -> 1
A26: 22 | B26: Sweetwater Care | C26: =COUNTIF('LTC Facilities'!$D$5:$D$316,$B26) -> 4 | D26: =SUMIF('LTC Facilities'!$D$5:$D$316,$B26,'LTC Facilities'!$E$5:$E$316) -> 338 | E26: =COUNTIFS('LTC Facilities'!$D$5:$D$316,$B26,'LTC Facilities'!$G$5:$G$316,"Metro") -> 3
A27: 23 | B27: American Baptist Homes of the Midwest | C27: =COUNTIF('LTC Facilities'!$D$5:$D$316,$B27) -> 2 | D27: =SUMIF('LTC Facilities'!$D$5:$D$316,$B27,'LTC Facilities'!$E$5:$E$316) -> 323 | E27: =COUNTIFS('LTC Facilities'!$D$5:$D$316,$B27,'LTC Facilities'!$G$5:$G$316,"Metro") -> 2
A28: 24 | B28: Erickson Senior Living | C28: =COUNTIF('LTC Facilities'!$D$5:$D$316,$B28) -> 1 | D28: =SUMIF('LTC Facilities'!$D$5:$D$316,$B28,'LTC Facilities'!$E$5:$E$316) -> 316 | E28: =COUNTIFS('LTC Facilities'!$D$5:$D$316,$B28,'LTC Facilities'!$G$5:$G$316,"Metro") -> 1 | F28: Wind Crest in Highlands Ranch — one of the largest single senior campuses in Colorado. Licensed beds understate it badly: ~1,300-1,500 unlicensed independent living apartments on top.
A29: 25 | B29: Eaton Senior Communities | C29: =COUNTIF('LTC Facilities'!$D$5:$D$316,$B29) -> 1 | D29: =SUMIF('LTC Facilities'!$D$5:$D$316,$B29,'LTC Facilities'!$E$5:$E$316) -> 300 | E29: =COUNTIFS('LTC Facilities'!$D$5:$D$316,$B29,'LTC Facilities'!$G$5:$G$316,"Metro") -> 1
A30: 26 | B30: Good Samaritan Society (Sanford Health) | C30: =COUNTIF('LTC Facilities'!$D$5:$D$316,$B30) -> 5 | D30: =SUMIF('LTC Facilities'!$D$5:$D$316,$B30,'LTC Facilities'!$E$5:$E$316) -> 228 | E30: =COUNTIFS('LTC Facilities'!$D$5:$D$316,$B30,'LTC Facilities'!$G$5:$G$316,"Metro") -> 0 | F30: Northern Colorado only — NO Denver metro presence.
A31: 27 | B31: CommonSpirit Health | C31: =COUNTIF('LTC Facilities'!$D$5:$D$316,$B31) -> 2 | D31: =SUMIF('LTC Facilities'!$D$5:$D$316,$B31,'LTC Facilities'!$E$5:$E$316) -> 215 | E31: =COUNTIFS('LTC Facilities'!$D$5:$D$316,$B31,'LTC Facilities'!$G$5:$G$316,"Metro") -> 1
A32: 28 | B32: Independent (MGL Partners dev.) | C32: =COUNTIF('LTC Facilities'!$D$5:$D$316,$B32) -> 1 | D32: =SUMIF('LTC Facilities'!$D$5:$D$316,$B32,'LTC Facilities'!$E$5:$E$316) -> 207 | E32: =COUNTIFS('LTC Facilities'!$D$5:$D$316,$B32,'LTC Facilities'!$G$5:$G$316,"Metro") -> 1
A33: 29 | B33: Legend Senior Living | C33: =COUNTIF('LTC Facilities'!$D$5:$D$316,$B33) -> 2 | D33: =SUMIF('LTC Facilities'!$D$5:$D$316,$B33,'LTC Facilities'!$E$5:$E$316) -> 206 | E33: =COUNTIFS('LTC Facilities'!$D$5:$D$316,$B33,'LTC Facilities'!$G$5:$G$316,"Metro") -> 1
A34: 30 | B34: Cogir Senior Living | C34: =COUNTIF('LTC Facilities'!$D$5:$D$316,$B34) -> 1 | D34: =SUMIF('LTC Facilities'!$D$5:$D$316,$B34,'LTC Facilities'!$E$5:$E$316) -> 165 | E34: =COUNTIFS('LTC Facilities'!$D$5:$D$316,$B34,'LTC Facilities'!$G$5:$G$316,"Metro") -> 1
A35: 31 | B35: Amira Senior Living | C35: =COUNTIF('LTC Facilities'!$D$5:$D$316,$B35) -> 1 | D35: =SUMIF('LTC Facilities'!$D$5:$D$316,$B35,'LTC Facilities'!$E$5:$E$316) -> 160 | E35: =COUNTIFS('LTC Facilities'!$D$5:$D$316,$B35,'LTC Facilities'!$G$5:$G$316,"Metro") -> 1
A36: 32 | B36: Gardens Care Senior Living | C36: =COUNTIF('LTC Facilities'!$D$5:$D$316,$B36) -> 3 | D36: =SUMIF('LTC Facilities'!$D$5:$D$316,$B36,'LTC Facilities'!$E$5:$E$316) -> 160 | E36: =COUNTIFS('LTC Facilities'!$D$5:$D$316,$B36,'LTC Facilities'!$G$5:$G$316,"Metro") -> 3
A37: 33 | B37: Volunteers of America National Services | C37: =COUNTIF('LTC Facilities'!$D$5:$D$316,$B37) -> 3 | D37: =SUMIF('LTC Facilities'!$D$5:$D$316,$B37,'LTC Facilities'!$E$5:$E$316) -> 146 | E37: =COUNTIFS('LTC Facilities'!$D$5:$D$316,$B37,'LTC Facilities'!$G$5:$G$316,"Metro") -> 0 | F37: VOA Colorado's metro footprint is unlicensed affordable senior housing, not licensed LTC.
A38: 34 | B38: Juniper Communities | C38: =COUNTIF('LTC Facilities'!$D$5:$D$316,$B38) -> 3 | D38: =SUMIF('LTC Facilities'!$D$5:$D$316,$B38,'LTC Facilities'!$E$5:$E$316) -> 135 | E38: =COUNTIFS('LTC Facilities'!$D$5:$D$316,$B38,'LTC Facilities'!$G$5:$G$316,"Metro") -> 3
A39: 35 | B39: Clear Choice Healthcare | C39: =COUNTIF('LTC Facilities'!$D$5:$D$316,$B39) -> 1 | D39: =SUMIF('LTC Facilities'!$D$5:$D$316,$B39,'LTC Facilities'!$E$5:$E$316) -> 133 | E39: =COUNTIFS('LTC Facilities'!$D$5:$D$316,$B39,'LTC Facilities'!$G$5:$G$316,"Metro") -> 1
A40: 36 | B40: Advanced Health Care | C40: =COUNTIF('LTC Facilities'!$D$5:$D$316,$B40) -> 3 | D40: =SUMIF('LTC Facilities'!$D$5:$D$316,$B40,'LTC Facilities'!$E$5:$E$316) -> 124 | E40: =COUNTIFS('LTC Facilities'!$D$5:$D$316,$B40,'LTC Facilities'!$G$5:$G$316,"Metro") -> 2
A41: 37 | B41: Covenant Living Communities | C41: =COUNTIF('LTC Facilities'!$D$5:$D$316,$B41) -> 1 | D41: =SUMIF('LTC Facilities'!$D$5:$D$316,$B41,'LTC Facilities'!$E$5:$E$316) -> 120 | E41: =COUNTIFS('LTC Facilities'!$D$5:$D$316,$B41,'LTC Facilities'!$G$5:$G$316,"Metro") -> 1
A42: 38 | B42: Solera Senior Living (Denver HQ) | C42: =COUNTIF('LTC Facilities'!$D$5:$D$316,$B42) -> 1 | D42: =SUMIF('LTC Facilities'!$D$5:$D$316,$B42,'LTC Facilities'!$E$5:$E$316) -> 105 | E42: =COUNTIFS('LTC Facilities'!$D$5:$D$316,$B42,'LTC Facilities'!$G$5:$G$316,"Metro") -> 1
A43: 39 | B43: Atria Senior Living | C43: =COUNTIF('LTC Facilities'!$D$5:$D$316,$B43) -> 1 | D43: =SUMIF('LTC Facilities'!$D$5:$D$316,$B43,'LTC Facilities'!$E$5:$E$316) -> 100 | E43: =COUNTIFS('LTC Facilities'!$D$5:$D$316,$B43,'LTC Facilities'!$G$5:$G$316,"Metro") -> 1
A44: 40 | B44: Cassia | C44: =COUNTIF('LTC Facilities'!$D$5:$D$316,$B44) -> 1 | D44: =SUMIF('LTC Facilities'!$D$5:$D$316,$B44,'LTC Facilities'!$E$5:$E$316) -> 44 | E44: =COUNTIFS('LTC Facilities'!$D$5:$D$316,$B44,'LTC Facilities'!$G$5:$G$316,"Metro") -> 0
A45: 41 | B45: Senior Lifestyle | C45: =COUNTIF('LTC Facilities'!$D$5:$D$316,$B45) -> 1 | D45: =SUMIF('LTC Facilities'!$D$5:$D$316,$B45,'LTC Facilities'!$E$5:$E$316) -> 42 | E45: =COUNTIFS('LTC Facilities'!$D$5:$D$316,$B45,'LTC Facilities'!$G$5:$G$316,"Metro") -> 0
A46: 42 | B46: Vi Living | C46: =COUNTIF('LTC Facilities'!$D$5:$D$316,$B46) -> 1 | D46: =SUMIF('LTC Facilities'!$D$5:$D$316,$B46,'LTC Facilities'!$E$5:$E$316) -> 24 | E46: =COUNTIFS('LTC Facilities'!$D$5:$D$316,$B46,'LTC Facilities'!$G$5:$G$316,"Metro") -> 1
A47: 43 | B47: WellAge Senior Living | C47: =COUNTIF('LTC Facilities'!$D$5:$D$316,$B47) -> 4 | D47: =SUMIF('LTC Facilities'!$D$5:$D$316,$B47,'LTC Facilities'!$E$5:$E$316) -> 0 | E47: =COUNTIFS('LTC Facilities'!$D$5:$D$316,$B47,'LTC Facilities'!$G$5:$G$316,"Metro") -> 1 | F47: MANAGEMENT COMPANY affiliated with the Vivage leadership group. Controls purchasing for buildings it doesn't own.
A48: 44 | B48: Independent nonprofit | C48: =COUNTIF('LTC Facilities'!$D$5:$D$316,$B48) -> 1 | D48: =SUMIF('LTC Facilities'!$D$5:$D$316,$B48,'LTC Facilities'!$E$5:$E$316) -> 0 | E48: =COUNTIFS('LTC Facilities'!$D$5:$D$316,$B48,'LTC Facilities'!$G$5:$G$316,"Metro") -> 1
B49: TOTAL | C49: =SUM(C5:C48) -> 268 | D49: =SUM(D5:D48) -> 27035 | E49: =SUM(E5:E48) -> 153
B51: Top 5 operators as % of all listed LTC beds: | D51: =SUM(D5:D9)/D49 -> 0.46447198

Sheet LTC Facilities
A1: Long-Term Care Facilities — Grouped by Corporate Operator
A2: Skilled nursing, assisted living, memory care and CCRCs. Operators ordered by total beds; facilities within each ordered largest to smallest.
A4: # | B4: Facility | C4: City | D4: Corporate Operator | E4: Licensed Beds | F4: Care Type | G4: Region | H4: Notes (add your own)
A5: The Ensign Group (Endura Healthcare) — 33 facilities (22 in metro), 3,664 licensed beds
A6: 1 | B6: Hampden Hills Post Acute | C6: Aurora | D6: The Ensign Group (Endura Healthcare) | E6: 218 | F6: Skilled nursing | G6: Metro
A7: 2 | B7: Oakwood Care and Rehabilitation | C7: Lakewood | D7: The Ensign Group (Endura Healthcare) | E7: 170 | F7: Skilled nursing | G7: Metro
A8: 3 | B8: Malley Transitional Care Center | C8: Northglenn | D8: The Ensign Group (Endura Healthcare) | E8: 162 | F8: Skilled nursing | G8: Metro
A9: 4 | B9: The Villas at Sunny Acres | C9: Thornton | D9: The Ensign Group (Endura Healthcare) | E9: 160 | F9: Skilled nursing | G9: Metro | H9: On CCRC campus
A10: 5 | B10: Parker Post Acute | C10: Parker | D10: The Ensign Group (Endura Healthcare) | E10: 154 | F10: Skilled nursing | G10: Metro
A11: 6 | B11: Rock Canyon Respiratory & Rehabilitation | C11: Pueblo | D11: The Ensign Group (Endura Healthcare) | E11: 151 | F11: Skilled nursing | G11: Outside metro
A12: 7 | B12: Boulder Canyon Health & Rehabilitation | C12: Boulder | D12: The Ensign Group (Endura Healthcare) | E12: 140 | F12: Skilled nursing | G12: Metro
A13: 8 | B13: Holly Heights Care & Rehabilitation | C13: Denver | D13: The Ensign Group (Endura Healthcare) | E13: 133 | F13: Skilled nursing | G13: Metro
A14: 9 | B14: Durango Health & Rehabilitation | C14: Durango | D14: The Ensign Group (Endura Healthcare) | E14: 133 | F14: Skilled nursing | G14: Outside metro
A15: 10 | B15: The Springs at St. Andrews Village | C15: Aurora | D15: The Ensign Group (Endura Healthcare) | E15: 130 | F15: SNF + assisted living | G15: Metro | H15: 58 SNF + 72 AL
A16: 11 | B16: Julia Temple Healthcare Center | C16: Englewood | D16: The Ensign Group (Endura Healthcare) | E16: 128 | F16: Skilled nursing | G16: Metro
A17: 12 | B17: City Park Healthcare & Rehabilitation | C17: Denver | D17: The Ensign Group (Endura Healthcare) | E17: 125 | F17: Skilled nursing | G17: Metro
A18: 13 | B18: Ridgeview Post Acute | C18: Commerce City | D18: The Ensign Group (Endura Healthcare) | E18: 112 | F18: Skilled nursing | G18: Metro
A19: 14 | B19: McIntosh Care & Rehabilitation | C19: Longmont | D19: The Ensign Group (Endura Healthcare) | E19: 110 | F19: Skilled nursing | G19: Metro
A20: 15 | B20: Brighton Care Center | C20: Brighton | D20: The Ensign Group (Endura Healthcare) | E20: 108 | F20: Skilled nursing | G20: Metro
A21: 16 | B21: Westlake Health & Rehabilitation | C21: Greeley | D21: The Ensign Group (Endura Healthcare) | E21: 107 | F21: Skilled nursing | G21: Extended
A22: 17 | B22: Lakeshore Post Acute | C22: Pueblo | D22: The Ensign Group (Endura Healthcare) | E22: 106 | F22: Skilled nursing | G22: Outside metro
A23: 18 | B23: Rehabilitation & Nursing Center of the Rockies | C23: Fort Collins | D23: The Ensign Group (Endura Healthcare) | E23: 106 | F23: Skilled nursing | G23: Extended
A24: 19 | B24: South Valley Post Acute | C24: Denver | D24: The Ensign Group (Endura Healthcare) | E24: 106 | F24: Skilled nursing | G24: Metro
A25: 20 | B25: Pelican Pointe Health & Rehabilitation | C25: Windsor | D25: The Ensign Group (Endura Healthcare) | E25: 104 | F25: Skilled nursing | G25: Extended
A26: 21 | B26: The Rehabilitation Center at Sandalwood | C26: Wheat Ridge | D26: The Ensign Group (Endura Healthcare) | E26: 103 | F26: Skilled nursing | G26: Metro
A27: 22 | B27: Broadview Health & Rehabilitation | C27: Greeley | D27: The Ensign Group (Endura Healthcare) | E27: 100 | F27: Skilled nursing | G27: Extended
... A38: 33 | B38: Littleton Care & Rehabilitation | C38: Littleton | D38: The Ensign Group (Endura Healthcare) | E38: 35 | F38: Skilled nursing | G38: Metro
A39: Life Care Centers of America — 22 facilities (12 in metro), 2,929 licensed beds
A40: 34 | B40: Life Care Center of Longmont | C40: Longmont | D40: Life Care Centers of America | E40: 257 | F40: SNF + assisted living | G40: Metro | H40: 187 SNF + 70 AL (The Bridge)
A41: 35 | B41: Briarwood Health Care Center | C41: Denver | D41: Life Care Centers of America | E41: 201 | F41: Skilled nursing | G41: Metro
A42: 36 | B42: Life Care Center of Greeley | C42: Greeley | D42: Life Care Centers of America | E42: 194 | F42: SNF + assisted living | G42: Extended | H42: 124 SNF + 70 AL (The Bridge)
A43: 37 | B43: Life Care Center of Pueblo | C43: Pueblo | D43: Life Care Centers of America | E43: 187 | F43: Skilled nursing | G43: Outside metro
A44: 38 | B44: University Park Care Center | C44: Pueblo | D44: Life Care Centers of America | E44: 180 | F44: Skilled nursing | G44: Outside metro
A45: 39 | B45: Life Care Center of Aurora | C45: Aurora | D45: Life Care Centers of America | E45: 166 | F45: Skilled nursing | G45: Metro
A46: 40 | B46: Hallmark Nursing Center | C46: Denver | D46: Life Care Centers of America | E46: 143 | F46: Skilled nursing | G46: Metro
A47: 41 | B47: Western Hills Health Care Center | C47: Lakewood | D47: Life Care Centers of America | E47: 140 | F47: Skilled nursing | G47: Metro
A48: 42 | B48: Life Care Center of Colorado Springs | C48: Colorado Springs | D48: Life Care Centers of America | E48: 121 | F48: Skilled nursing | G48: Extended
A49: 43 | B49: Life Care Center of Evergreen | C49: Evergreen | D49: Life Care Centers of America | E49: 120 | F49: Skilled nursing | G49: Metro
A50: 44 | B50: Life Care Center of Westminster | C50: Westminster | D50: Life Care Centers of America | E50: 120 | F50: Skilled nursing | G50: Metro
A51: 45 | B51: Life Care Center of Littleton | C51: Littleton | D51: Life Care Centers of America | E51: 120 | F51: Skilled nursing | G51: Metro
A52: 46 | B52: Life Care Center of Stonegate | C52: Parker | D52: Life Care Centers of America | E52: 120 | F52: Skilled nursing | G52: Metro
A53: 47 | B53: Valley View Villa | C53: Fort Morgan | D53: Life Care Centers of America | E53: 120 | F53: Skilled nursing | G53: Outside metro
A54: 48 | B54: Garden Terrace Alzheimer's Center of Excellence | C54: Aurora | D54: Life Care Centers of America | E54: 120 | F54: SNF / memory care | G54: Metro
... A61: 55 | B61: Canon Lodge Care Center | C61: Canon City | D61: Life Care Centers of America | E61: 60 | F61: Skilled nursing | G61: Outside metro
A62: PACS Group (NYSE: PACS) — 19 facilities (14 in metro), 2,409 licensed beds
A63: 56 | B63: Skylake Post Acute | C63: Thornton | D63: PACS Group (NYSE: PACS) | E63: 242 | F63: Skilled nursing | G63: Metro
A64: 57 | B64: Pikes Peak Post Acute | C64: Colorado Springs | D64: PACS Group (NYSE: PACS) | E64: 210 | F64: Skilled nursing | G64: Extended
A65: 58 | B65: Mountain View Post Acute | C65: Colorado Springs | D65: PACS Group (NYSE: PACS) | E65: 180 | F65: Skilled nursing | G65: Extended
A66: 59 | B66: Boulder Post Acute | C66: Boulder | D66: PACS Group (NYSE: PACS) | E66: 162 | F66: Skilled nursing | G66: Metro
A67: 60 | B67: Hilltop Park Post Acute | C67: Denver | D67: PACS Group (NYSE: PACS) | E67: 162 | F67: Skilled nursing | G67: Metro
A68: 61 | B68: Winding Trails Post Acute | C68: Boulder | D68: PACS Group (NYSE: PACS) | E68: 150 | F68: Skilled nursing | G68: Metro
A69: 62 | B69: Atlas Post Acute | C69: Pueblo | D69: PACS Group (NYSE: PACS) | E69: 146 | F69: Skilled nursing | G69: Outside metro
A70: 63 | B70: Coal Creek Post Acute & Assisted Living | C70: Lafayette | D70: PACS Group (NYSE: PACS) | E70: 130 | F70: SNF + assisted living | G70: Metro | H70: 70 SNF + 60 AL
A71: 64 | B71: Highline Post Acute | C71: Denver | D71: PACS Group (NYSE: PACS) | E71: 125 | F71: Skilled nursing | G71: Metro
A72: 65 | B72: Heights Care & Rehabilitation | C72: Denver | D72: PACS Group (NYSE: PACS) | E72: 110 | F72: Skilled nursing | G72: Metro
A73: 66 | B73: Lakewood Post Acute & Rehabilitation | C73: Lakewood | D73: PACS Group (NYSE: PACS) | E73: 108 | F73: Skilled nursing | G73: Metro
A74: 67 | B74: Riverdale Post Acute | C74: Brighton | D74: PACS Group (NYSE: PACS) | E74: 105 | F74: Skilled nursing | G74: Metro
A75: 68 | B75: Sierra Post Acute | C75: Lakewood | D75: PACS Group (NYSE: PACS) | E75: 102 | F75: Skilled nursing | G75: Metro
A76: 69 | B76: Red Cliffs Post Acute | C76: Grand Junction | D76: PACS Group (NYSE: PACS) | E76: 89 | F76: Skilled nursing | G76: Outside metro
A77: 70 | B77: Amberwood Post Acute | C77: Denver | D77: PACS Group (NYSE: PACS) | E77: 88 | F77: Skilled nursing | G77: Metro
A78: 71 | B78: Westwood Post Acute | C78: Denver | D78: PACS Group (NYSE: PACS) | E78: 85 | F78: Skilled nursing | G78: Metro
A79: 72 | B79: Lakeside Post Acute | C79: Wheat Ridge | D79: PACS Group (NYSE: PACS) | E79: 78 | F79: Skilled nursing | G79: Metro
A80: 73 | B80: Eagle Ridge Post Acute | C80: Grand Junction | D80: PACS Group (NYSE: PACS) | E80: 70 | F80: Skilled nursing | G80: Outside metro
A81: 74 | B81: Brookshire Post Acute | C81: Denver | D81: PACS Group (NYSE: PACS) | E81: 67 | F81: Skilled nursing | G81: Metro
A82: Vivage-Beecan Senior Living — 23 facilities (15 in metro), 1,909 licensed beds
A83: 75 | B83: Harmony Pointe Nursing Center | C83: Lakewood | D83: Vivage-Beecan Senior Living | E83: 125 | F83: Skilled nursing | G83: Metro | H83: Licensed under Long Peak Operating Co.
A84: 76 | B84: Arbor View Care Center | C84: Arvada | D84: Vivage-Beecan Senior Living | E84: 110 | F84: Skilled nursing | G84: Metro | H84: Licensed under Long Peak Operating Co.
A85: 77 | B85: Cambridge Care Center | C85: Lakewood | D85: Vivage-Beecan Senior Living | E85: 110 | F85: Skilled nursing | G85: Metro
A86: 78 | B86: Crestmoor Care Center | C86: Denver | D86: Vivage-Beecan Senior Living | E86: 108 | F86: Skilled nursing | G86: Metro | H86: Licensed under Long Peak Operating Co.
A87: 79 | B87: University Heights Care Center | C87: Aurora | D87: Vivage-Beecan Senior Living | E87: 105 | F87: Skilled nursing | G87: Metro | H87: Licensed under Long Peak Operating Co.
A88: 80 | B88: Thornton Care Center | C88: Thornton | D88: Vivage-Beecan Senior Living | E88: 101 | F88: Skilled nursing | G88: Metro | H88: Licensed under Long Peak Operating Co.
A89: 81 | B89: Aviva at Fitzsimons | C89: Aurora | D89: Vivage-Beecan Senior Living | E89: 100 | F89: Skilled nursing | G89: Metro
A90: 82 | B90: Canyon View Care Center | C90: Palisade | D90: Vivage-Beecan Senior Living | E90: 88 | F90: Skilled nursing | G90: Outside metro
A91: 83 | B91: Allison Care Center | C91: Lakewood | D91: Vivage-Beecan Senior Living | E91: 85 | F91: Skilled nursing | G91: Metro | H91: Licensed under Long Peak Operating Co.
A92: 84 | B92: Devonshire Care Center | C92: Sterling | D92: Vivage-Beecan Senior Living | E92: 84 | F92: Skilled nursing | G92: Outside metro | H92: Licensed under Long Peak Operating Co.
A93: 85 | B93: Denver North Care Center | C93: Denver | D93: Vivage-Beecan Senior Living | E93: 82 | F93: Skilled nursing | G93: Metro
A94: 86 | B94: Colorow Care Center | C94: Olathe | D94: Vivage-Beecan Senior Living | E94: 82 | F94: Skilled nursing | G94: Outside metro
A95: 87 | B95: Wellsprings Care Center | C95: Englewood | D95: Vivage-Beecan Senior Living | E95: 81 | F95: Skilled nursing | G95: Metro
A96: 88 | B96: Clear Creek Care Center | C96: Westminster | D96: Vivage-Beecan Senior Living | E96: 80 | F96: Skilled nursing | G96: Metro
A97: 89 | B97: Uptown Healthcare Center | C97: Denver | D97: Vivage-Beecan Senior Living | E97: 79 | F97: Skilled nursing | G97: Metro
A98: 90 | B98: Hope Springs Care Center | C98: Montrose | D98: Vivage-Beecan Senior Living | E98: 74 | F98: Skilled nursing | G98: Outside metro
A99: 91 | B99: Parkview Care Center | C99: Denver | D99: Vivage-Beecan Senior Living | E99: 73 | F99: Skilled nursing | G99: Metro | H99: Licensed under Long Peak Operating Co.
A100: 92 | B100: Rowan Community | C100: Denver | D100: Vivage-Beecan Senior Living | E100: 65 | F100: Skilled nursing | G100: Metro
A101: 93 | B101: Wheatridge Manor Care Center | C101: Wheat Ridge | D101: Vivage-Beecan Senior Living | E101: 65 | F101: Skilled nursing | G101: Metro
A102: 94 | B102: Valley View Health Care Center | C102: Canon City | D102: Vivage-Beecan Senior Living | E102: 60 | F102: Skilled nursing | G102: Outside metro
A103: 95 | B103: Bluestem Village | C103: La Junta | D103: Vivage-Beecan Senior Living | E103: 56 | F103: Skilled nursing | G103: Outside metro
A104: 96 | B104: Regent Park Nursing & Rehab | C104: Holyoke | D104: Vivage-Beecan Senior Living | E104: 51 | F104: Skilled nursing | G104: Outside metro
A105: 97 | B105: Holly Nursing Care Center | C105: Holly | D105: Vivage-Beecan Senior Living | E105: 45 | F105: Skilled nursing | G105: Outside metro
A106: Stellar Senior Living — 12 facilities (5 in metro), 1,646 licensed beds
A107: 98 | B107: Lakewood Reserve | C107: Lakewood | D107: Stellar Senior Living | E107: 274 | F107: AL / memory care / IL | G107: Metro | H107: LARGEST non-hospital LTC building in the metro
A108: 99 | B108: Cherrelyn Healthcare Center | C108: Littleton | D108: Stellar Senior Living | E108: 190 | F108: Skilled nursing | G108: Metro
A109: 100 | B109: Bear Creek Senior Living | C109: Colorado Springs | D109: Stellar Senior Living | E109: 182 | F109: AL + SNF | G109: Extended | H109: 137 AL + 45 SNF
A110: 101 | B110: Acoya Cherry Creek | C110: Denver | D110: Stellar Senior Living | E110: 167 | F110: AL / IL / memory care | G110: Metro
A111: 102 | B111: The Grand at Broomfield | C111: Broomfield | D111: Stellar Senior Living | E111: 135 | F111: AL / IL / memory care | G111: Metro
A112: 103 | B112: Cedars Healthcare Center | C112: Lakewood | D112: Stellar Senior Living | E112: 130 | F112: Skilled nursing | G112: Metro
A113: 104 | B113: Winslow Court | C113: Colorado Springs | D113: Stellar Senior Living | E113: 128 | F113: Assisted living | G113: Extended
A114: 105 | B114: La Villa Grande Care Center | C114: Grand Junction | D114: Stellar Senior Living | E114: 96 | F114: SNF / AL | G114: Outside metro
A115: 106 | B115: Springs Village Care Center | C115: Colorado Springs | D115: Stellar Senior Living | E115: 91 | F115: Skilled nursing | G115: Extended
A116: 107 | B116: Mantey Heights Rehabilitation | C116: Grand Junction | D116: Stellar Senior Living | E116: 88 | F116: Skilled nursing | G116: Outside metro
A117: 108 | B117: Skyline Ridge Nursing & Rehab | C117: Canon City | D117: Stellar Senior Living | E117: 85 | F117: Skilled nursing | G117: Outside metro
...

Sheet Other Facilities
A1: Other Healthcare Facilities — Denver Metro
A2: Everything that is not a general acute-care hospital or a nursing home. Categories ordered by likely cleaning-supply value; entries within each ordered largest to smallest.
A4: # | B4: Facility / Organization | C4: City | D4: Parent / Operator | E4: Size | F4: Unit | G4: Category | H4: Notes (add your own)
A5: BEHAVIORAL HEALTH / PSYCHIATRIC HOSPITALS — 8 entries
A6: 1 | B6: Colorado Mental Health Hospital in Fort Logan | C6: Denver | D6: State of Colorado (CDHS) | E6: 154 | F6: licensed beds | G6: Behavioral health / psychiatric hospitals | H6: Sources vary 94-154; 154 is the CDPHE licensed figure
A7: 2 | B7: West Pines Behavioral Hospital | C7: Westminster | D7: Intermountain Health + Acadia Healthcare JV | E7: 144 | F7: licensed beds | G7: Behavioral health / psychiatric hospitals | H7: Opened 2024 - new build
A8: 3 | B8: HCA HealthONE Mental Health & Wellness Center | C8: Aurora | D8: HCA Healthcare | E8: 120 | F8: licensed beds | G8: Behavioral health / psychiatric hospitals | H8: Part of HCA HealthONE Aurora
A9: 4 | B9: Centennial Peaks Hospital | C9: Louisville | D9: Universal Health Services (UHS) | E9: 104 | F9: licensed beds | G9: Behavioral health / psychiatric hospitals
A10: 5 | B10: Denver Springs | C10: Englewood | D10: Lifepoint Behavioral Health | E10: 96 | F10: licensed beds | G10: Behavioral health / psychiatric hospitals | H10: Formerly Springstone
A11: 6 | B11: Highlands Behavioral Health System | C11: Highlands Ranch | D11: Universal Health Services (UHS) | E11: 86 | F11: licensed beds | G11: Behavioral health / psychiatric hospitals
A12: 7 | B12: Eating Recovery Center - Lowry | C12: Denver | D12: Eating Recovery Center / Pathlight (PE-backed) | E12: 72 | F12: licensed beds | G12: Behavioral health / psychiatric hospitals
A13: 8 | B13: Eating Recovery Center - A Behavioral Hospital | C13: Denver | D13: Eating Recovery Center / Pathlight (PE-backed) | E13: 36 | F13: licensed beds | G13: Behavioral health / psychiatric hospitals
A14: INPATIENT REHABILITATION HOSPITALS — 8 entries
A15: 9 | B15: Craig Hospital | C15: Englewood | D15: Independent nonprofit | E15: 93 | F15: licensed beds | G15: Inpatient rehabilitation hospitals | H15: National-destination spinal cord injury / TBI rehab. Also appears on the Hospitals tab
A16: 10 | B16: HCA HealthONE Spalding Rehabilitation | C16: Aurora | D16: HCA Healthcare | E16: 78 | F16: licensed beds | G16: Inpatient rehabilitation hospitals | H16: Colorado's first licensed acute rehab hospital
A17: 11 | B17: Encompass Health Rehabilitation Hospital of Littleton | C17: Littleton | D17: Encompass Health (NYSE: EHC) | E17: 60 | F17: licensed beds | G17: Inpatient rehabilitation hospitals | H17: Only Encompass IRF in the metro
A18: 12 | B18: PAM Health Rehabilitation Hospital of Golden | C18: Golden | D18: PAM Health | E18: 50 | F18: licensed beds | G18: Inpatient rehabilitation hospitals
A19: 13 | B19: Reunion Rehabilitation Hospital Denver | C19: Denver | D19: Nobis Rehabilitation Partners | E19: 40 | F19: licensed beds | G19: Inpatient rehabilitation hospitals | H19: Central Park
A20: 14 | B20: Reunion Rehabilitation Hospital Inverness | C20: Englewood | D20: Nobis Rehabilitation Partners | E20: 40 | F20: licensed beds | G20: Inpatient rehabilitation hospitals | H20: ~49,000 SF
A21: 15 | B21: PAM Health Rehabilitation Hospital of Westminster | C21: Westminster | D21: PAM Health | E21: 36 | F21: licensed beds | G21: Inpatient rehabilitation hospitals
A22: 16 | B22: Denver Regional Rehabilitation Hospital | C22: Thornton | D22: Vibra Healthcare | E22: 31 | F22: licensed beds | G22: Inpatient rehabilitation hospitals | H22: Co-located on the Vibra Hospital of Denver campus
A23: LONG-TERM ACUTE CARE HOSPITALS (LTACH) — 5 entries
A24: 17 | B24: Kindred Hospital - Denver | C24: Denver | D24: ScionHealth / Kindred LTAC | E24: 81 | F24: licensed beds | G24: Long-term acute care hospitals (LTACH) | H24: Ownership in flux - verify current parent
A25: 18 | B25: PAM Health Specialty Hospital of Denver | C25: Denver | D25: PAM Health | E25: 63 | F25: licensed beds | G25: Long-term acute care hospitals (LTACH)
A26: 19 | B26: Vibra Hospital of Denver | C26: Thornton | D26: Vibra Healthcare | E26: 54 | F26: licensed beds | G26: Long-term acute care hospitals (LTACH)
A27: 20 | B27: Kindred Hospital Aurora | C27: Aurora | D27: ScionHealth / Kindred LTAC | E27: 37 | F27: licensed beds | G27: Long-term acute care hospitals (LTACH)
A28: 21 | B28: Kindred Hospital - Denver South | C28: Denver | D28: ScionHealth / Kindred LTAC | E28: 28 | F28: licensed beds | G28: Long-term acute care hospitals (LTACH)
A29: AMBULATORY SURGERY CENTERS (ASCS) — 6 entries
A30: 22 | B30: Denver metro ASCs - ALL OPERATORS | C30: Metro-wide | D30: Various | E30: 90 | F30: centers (approx.) | G30: Ambulatory surgery centers (ASCs) | H30: 135 Medicare-certified ASCs statewide; ~85-95 in the metro. By county: Arapahoe ~20, Douglas ~17, Denver ~15, Jefferson ~15, Boulder ~14, Adams ~6
A31: 23 | B31: HCA HealthONE Ambulatory Surgical Centers | C31: Denver | D31: HCA Healthcare | E31: 13 | F31: centers (approx.) | G31: Ambulatory surgery centers (ASCs) | H31: Largest single metro ASC network. HQ 4900 S Monaco St. Includes Rose Surgical, Sky Ridge Surgical, North Suburban Surgery
A32: 24 | B32: UCHealth surgery centers | C32: Metro-wide | D32: UCHealth | E32: 3 | F32: centers | G32: Ambulatory surgery centers (ASCs) | H32: Cherry Creek North, Inverness Orthopedics & Spine, Longs Peak
A33: 25 | B33: Endoscopy Center of the Rockies | C33: Boulder County | D33: Independent GI group | E33: 3 | F33: centers | G33: Ambulatory surgery centers (ASCs) | H33: Boulder, Longmont, Lafayette
A34: 26 | B34: Kaiser Permanente ASCs | C34: Denver / Lone Tree | D34: Kaiser Permanente | E34: 2 | F34: centers | G34: Ambulatory surgery centers (ASCs) | H34: Franklin St (Denver) and Lone Tree
A35: 27 | B35: SCA Health / USPI / AmSurg / Surgery Partners holdings | C35: Metro-wide | D35: Optum, Tenet, Envision, Surgery Partners | F35: not disclosed | G35: Ambulatory surgery centers (ASCs) | H35: National chains hold Colorado stakes but operate under local physician-JV LLC names - not brandable from public sources
A36: DIALYSIS CENTERS — 5 entries
A37: 28 | B37: DaVita Inc. | C37: Denver (HQ) | D37: DaVita Inc. (NYSE: DVA) | E37: 30 | F37: clinics (approx.) | G37: Dialysis centers | H37: HEADQUARTERED IN DENVER (2000 16th St). ~2,600+ US clinics. Metro clinics use place-name branding
A38: 29 | B38: Fresenius Kidney Care | C38: Metro-wide | D38: Fresenius Medical Care | E38: 12 | F38: clinics (approx.) | G38: Dialysis centers | H38: Pavilion, Stapleton, Sloans Lake, Lowry, S. Denver, NE Denver, E. Denver, W. Belleview, W. Hampden, Castle Rock
A39: 30 | B39: Independent 'Kidney Center of...' clinics | C39: Metro-wide | D39: Physician-owned / DaVita JV | E39: 5 | F39: clinics (approx.) | G39: Dialysis centers | H39: Northridge, Westminster, Longmont, Lafayette, Parker
A40: 31 | B40: Hospital-based / academic dialysis | C40: Aurora | D40: UCHealth / Children's Colorado | E40: 3 | F40: units | G40: Dialysis centers | H40: UCH Dialysis Services; Children's Colorado Kidney Center
A41: 32 | B41: US Renal Care | C41: Aurora / Lone Tree | D41: US Renal Care | E41: 3 | F41: clinics | G41: Dialysis centers | H41: Altitude Dialysis (Aurora), Lone Tree
A42: MULTI-SITE CLINIC NETWORKS — 9 entries
A43: 33 | B43: Kaiser Permanente Colorado | C43: Metro-wide | D43: Kaiser Foundation Health Plan + Colorado Permanente Medical Group | E43: 34 | F43: medical offices | G43: Multi-site clinic networks | H43: 502,410 members; 6,522 physicians and employees. State's largest nonprofit provider. OWNS NO HOSPITALS
A44: 34 | B44: Denver Health community & school-based health centers | C44: Metro-wide | D44: Denver Health (public authority) | E44: 28 | F44: sites | G44: Multi-site clinic networks | H44: 9 community health centers + 18-20 school-based centers + Webb Center. 271,089 patients / 1.4M visits (2025)
A45: 35 | B45: New West Physicians | C45: Metro-wide | D45: Optum (UnitedHealth Group) | E45: 20 | F45: clinics (approx.) | G45: Multi-site clinic networks | H45: Largest independent primary-care group pre-acquisition; now core of Optum Colorado
A46: 36 | B46: STRIDE Community Health Center | C46: Metro-wide | D46: FQHC | E46: 11 | F46: clinics | G46: Multi-site clinic networks | H46: Denver, Aurora, Englewood, Wheat Ridge, Lakewood
A47: 37 | B47: Clinica Family Health & Wellness | C47: Lafayette | D47: FQHC | E47: 8 | F47: clinics (approx.) | G47: Multi-site clinic networks | H47: Adams, Boulder, Broomfield, Gilpin counties
A48: 38 | B48: Salud Family Health Centers | C48: Fort Lupton | D48: FQHC | E48: 5 | F48: metro clinics | G48: Multi-site clinic networks | H48: 13 statewide. Brighton, Commerce City, Longmont, Aurora
A49: 39 | B49: Colorado Coalition for the Homeless | C49: Denver | D49: FQHC | E49: 5 | F49: clinics (approx.) | G49: Multi-site clinic networks | H49: Stout Street Health Center
A50: 40 | B50: Peak Vista Community Health Centers | C50: Metro-wide | D50: FQHC | E50: 3 | F50: metro clinics (approx.) | G50: Multi-site clinic networks | H50: Colorado Springs-based; also serves Adams, Arapahoe, Douglas, Elbert
A51: 41 | B51: Tepeyac Community Health Center | C51: Denver | D51: FQHC | E51: 2 | F51: clinics | G51: Multi-site clinic networks | H51: Globeville / Elyria-Swansea
A52: FREESTANDING EMERGENCY DEPARTMENTS — 5 entries
A53: 42 | B53: AdventHealth freestanding ERs | C53: Metro-wide | D53: AdventHealth | E53: 6 | F53: locations | G53: Freestanding emergency departments | H53: Southlands (Aurora), Meridian (Parker), Southmoor (Denver), West Littleton, Highlands Ranch, Aurora Highlands
A54: 43 | B54: Intermountain Health emergency & urgent care | C54: Metro-wide | D54: Intermountain Health | E54: 5 | F54: locations | G54: Freestanding emergency departments | H54: Northglenn, Golden, Lakewood, Arvada, 84th Ave (Westminster)
A55: 44 | B55: UCHealth freestanding ERs | C55: Metro-wide | D55: UCHealth | E55: 5 | F55: locations | G55: Freestanding emergency departments | H55: Commerce City, Thornton, Arvada, Aurora Central, Green Valley Ranch
A56: 45 | B56: HCA HealthONE freestanding ERs | C56: Metro-wide | D56: HCA Healthcare | E56: 5 | F56: locations | G56: Freestanding emergency departments | H56: Northeast (Thornton), Belmar (Lakewood), Southwest (Littleton), South Parker, Central Park (Denver)
A57: 46 | B57: Boulder Community Health - Community Medical Center ED | C57: Lafayette | D57: Boulder Community Health | E57: 1 | F57: location | G57: Freestanding emergency departments
A58: URGENT CARE CHAINS — 6 entries
A59: 47 | B59: Concentra | C59: Metro-wide | D59: Select Medical Corporation | E59: 18 | F59: locations | G59: Urgent care chains | H59: Largest single urgent-care footprint in the metro; primarily occupational medicine / workers' comp
A60: 48 | B60: AFC Urgent Care | C60: Metro-wide | D60: AFC Franchising (franchisee-owned) | E60: 18 | F60: locations (approx.) | G60: Urgent care chains | H60: 28 statewide
A61: 49 | B61: UCHealth Urgent Care | C61: Metro-wide | D61: UCHealth | E61: 17 | F61: locations (approx.) | G61: Urgent care chains | H61: Count not published; many co-located with FSEDs
A62: 50 | B62: Independent / Peak Urgent Care / CityDoc | C62: Metro-wide | D62: Various | E62: 15 | F62: locations (approx.) | G62: Urgent care chains | H62: Highly fragmented; counts unverified
A63: 51 | B63: NextCare Urgent Care | C63: Metro-wide | D63: NextCare Holdings (PE-backed) | E63: 7 | F63: locations (approx.) | G63: Urgent care chains
A64: 52 | B64: Kaiser Permanente urgent care | C64: Metro-wide | D64: Kaiser Permanente | E64: 6 | F64: locations | G64: Urgent care chains | H64: Inside medical office buildings
A65: OCCUPATIONAL HEALTH — 5 entries
A66: 53 | B66: Concentra | C66: Metro-wide | D66: Select Medical Corporation | E66: 18 | F66: locations | G66: Occupational health | H66: Dominant occ-med network: Aurora x3, Boulder, Broomfield, Centennial, Central Park, Cherry Creek, S. Broadway, Downtown, Highlands Ranch, Lakewood, Littleton, Longmont, N. Denver, Parker, Thornton x2
A67: 54 | B67: Rocky Mountain Regional VA + community-based outpatient clinics | C67: Aurora | D67: US Dept. of Veterans Affairs | E67: 7 | F67: sites | G67: Occupational health | H67: 1 hospital + ~6 metro CBOCs (Golden, Aurora, Denver, Jewell, Boulder area)
A68: 55 | B68: UCHealth Occupational Medicine / WorkMed | C68: Metro-wide | D68: UCHealth | E68: 5 | F68: locations (approx.) | G68: Occupational health
A69: 56 | B69: HealthONE Occupational Health / WorkWell | C69: Metro-wide | D69: HCA Healthcare | E69: 4 | F69: locations (approx.) | G69: Occupational health
A70: 57 | B70: Employer on-site clinics | C70: Metro-wide | D70: Various employers | F70: not licensed | G70: Occupational health | H70: Lockheed Martin (Waterton Canyon), Ball Aerospace, Denver International Airport, Amazon fulfillment centers, large school districts
A71: CANCER CENTERS — 5 entries
A72: 58 | B72: Rocky Mountain Cancer Centers | C72: Metro-wide | D72: The US Oncology Network / McKesson | E72: 12 | F72: metro locations | G72: Cancer centers | H72: 17-20 statewide. Largest community oncology group in Colorado
A73: 59 | B73: UCHealth Cancer Care / CU Cancer Center | C73: Metro-wide | D73: UCHealth + University of Colorado | E73: 8 | F73: locations (approx.) | G73: Cancer centers | H73: NCI-designated Comprehensive Cancer Center at Anschutz
A74: 60 | B74: Sarah Cannon Cancer Institute at HealthONE | C74: Metro-wide | D74: HCA Healthcare | E74: 6 | F74: locations (approx.) | G74: Cancer centers
A75: 61 | B75: AdventHealth cancer centers | C75: Metro-wide | D75: AdventHealth | E75: 5 | F75: locations (approx.) | G75: Cancer centers
A76: 62 | B76: Intermountain cancer centers (Saint Joseph, Lutheran) | C76: Metro-wide | D76: Intermountain Health | E76: 5 | F76: locations (approx.) | G76: Cancer centers
A77: IMAGING CENTER CHAINS — 4 entries
A78: 63 | B78: Hospital-owned outpatient imaging | C78: Metro-wide | D78: UCHealth / HCA / AdventHealth / Intermountain | E78: 30 | F78: locations (approx.) | G78: Imaging center chains
A79: 64 | B79: Invision Sally Jobe | C79: Metro-wide | D79: Radiology Imaging Associates / Envision (unconfirmed) | E79: 10 | F79: locations (approx.) | G79: Imaging center chains | H79: Historic large Denver outpatient imaging network; current corporate parent unverified
A80: 65 | B80: Touchstone Medical Imaging | C80: Metro-wide | D80: Touchstone Imaging (PE-owned) | E80: 8 | F80: locations | G80: Imaging center chains | H80: Aurora, Castle Rock, Dry Creek/DTC, Lafayette, Lakewood, Thornton, Uptown Denver, Wheat Ridge
A81: 66 | B81: Health Images | C81: Metro-wide | D81: Health Images (Colorado Springs HQ) | E81: 4 | F81: metro locations | G81: Imaging center chains | H81: Arvada, Westminster, Greenwood Village, Lakewood. 6 in Colorado
A82: COMMUNITY MENTAL HEALTH CENTERS (MULTI-SITE) — 5 entries
A83: 67 | B83: WellPower (formerly Mental Health Center of Denver) | C83: Denver | D83: Independent nonprofit (BHA-designated) | E83: 30 | F83: sites (approx.) | G83: Community mental health centers (multi-site) | H83: Largest community mental health center in the state; includes school-based and supportive housing sites
A84: 68 | B84: Jefferson Center for Mental Health | C84: Lakewood | D84: Independent nonprofit | E84: 15 | F84: sites (approx.) | G84: Community mental health centers (multi-site) | H84: Jefferson, Clear Creek, Gilpin counties
A85: 69 | B85: Mental Health Partners | C85: Boulder | D85: Independent nonprofit | E85: 10 | F85: sites (approx.) | G85: Community mental health centers (multi-site) | H85: Boulder & Broomfield counties
A86: 70 | B86: AllHealth Network | C86: Englewood | D86: Independent nonprofit | E86: 10 | F86: sites (approx.) | G86: Community mental health centers (multi-site) | H86: Arapahoe & Douglas counties
A87: 71 | B87: Community Reach Center | C87: Thornton | D87: Independent nonprofit | E87: 8 | F87: sites (approx.) | G87: Community mental health centers (multi-site) | H87: Adams County
A88: HOSPICE — 8 entries
A89: 72 | B89: Denver metro hospice agencies - ALL | C89: Metro-wide | D89: Various | E89: 40 | F89: agencies (approx.) | G89: Hospice | H89: Extremely fragmented. 24 in Arapahoe County alone, concentrated in Greenwood Village/Centennial
A90: 73 | B90: The Denver Hospice | C90: Denver | D90: Care Synergy (nonprofit network) | E90: 24 | F90: inpatient beds | G90: Hospice | H90: Since 1978. Largest inpatient hospice in the metro (8289 E Lowry Blvd). Care Synergy also owns Colorado VNA, Colorado PACE, Pathways, Pikes Peak Hospice
A91: 74 | B91: HCA HealthONE Hospice & Family Care | C91: Greenwood Village | D91: HCA Healthcare | F91: agency | G91: Hospice
A92: 75 | B92: Agape Healthcare | C92: Metro-wide | D92: Independent / PE | F92: agency | G92: Hospice | H92: Large metro provider
A93: 76 | B93: TRU Community Care | C93: Lafayette | D93: Independent nonprofit | F93: agency | G93: Hospice | H93: Boulder County
A94: 77 | B94: Bristol Hospice - Denver | C94: Denver | D94: Bristol Hospice (PE-backed) | F94: agency | G94: Hospice
A95: 78 | B95: Brighton Hospice Colorado | C95: Metro-wide | D95: Brighton Hospice (PE-backed) | F95: agency | G95: Hospice
A96: 79 | B96: Gentiva | C96: Castle Rock | D96: Gentiva (formerly Kindred at Home) | F96: agency | G96: Hospice
A97: HOME HEALTH — 3 entries
A98: 80 | B98: Denver metro licensed home health & home care agencies | C98: Metro-wide | D98: Various | F98: hundreds | G98: Home health | H98: CDPHE tracks Home Health Agency and Home Care Agency as separate license classes
A99: 81 | B99: Colorado Visiting Nurse Association | C99: Metro-wide | D99: Care Synergy | F99: agency | G99: Home health | H99: Established 1889
A100: 82 | B100: UCHealth Home Care / Denver Health Home Care / BAYADA / Interim / Amedisys / Enhabit | C100: Metro-wide | D100: Various | F100: agencies | G100: Home health | H100: Largest metro home health operators
A101: SPECIALTY & RESEARCH — 4 entries
...
